{
	"group": [{
		"title": "一楼",
		"val": "one"
	}, {
		"title": "二楼",
		"val": "two"
	}],
	"list": [{
		"title": "儿童房灯",
		"id": "1",
		"group": "two",
		"key1": "POWER",
		"mode": "light",
		"stat": "OFF",
		"JSON": "loog/gelou/STATE",
		"name": "gelou",
		"cmdoff": "off",
		"Publish": "loog/gelou/cmnd/POWER",
		"unit": "",
		"Subscribe": "loog/gelou/POWER",
		"cmdon": "on"
	}, {
		"title": "卧室灯",
		"id": "2",
		"group": "two",
		"key1": "POWER",
		"mode": "light",
		"stat": "OFF",
		"JSON": "loog/woshi/STATE",
		"name": "woshi",
		"cmdoff": "off",
		"Publish": "loog/woshi/cmnd/POWER",
		"unit": "",
		"Subscribe": "loog/woshi/POWER",
		"cmdon": "on"
	}, {
		"title": "楼上",
		"id": "3",
		"group": "two",
		"key1": "POWER",
		"mode": "light",
		"stat": "OFF",
		"JSON": "loog/zhongting/STATE",
		"name": "zhongting",
		"cmdoff": "off",
		"Publish": "loog/zhongting/cmnd/POWER",
		"unit": "",
		"Subscribe": "loog/zhongting/POWER",
		"cmdon": "on"
	}, {
		"title": "客厅灯",
		"id": "4",
		"group": "one",
		"key1": "POWER",
		"mode": "light",
		"stat": "OFF",
		"JSON": "loog/keting/RESULT",
		"name": "keting",
		"cmdoff": "off",
		"Publish": "loog/keting/cmnd/POWER",
		"unit": "",
		"Subscribe": "loog/keting/POWER",
		"cmdon": "on"
	}, {
		"title": "洗手间",
		"id": "5",
		"group": "one",
		"key1": "POWER",
		"mode": "light",
		"stat": "OFF",
		"JSON": "loog/xishoujian/STATE",
		"name": "xishoujian",
		"cmdoff": "off",
		"Publish": "loog/xishoujian/cmnd/POWER",
		"unit": "",
		"Subscribe": "loog/xishoujian/POWER",
		"cmdon": "on"
	}, {
		"title": "书房",
		"id": "6",
		"group": "one",
		"key1": "POWER",
		"mode": "light",
		"stat": "OFF",
		"JSON": "loog/shufang/STATE",
		"name": "shufang",
		"cmdoff": "off",
		"Publish": "loog/shufang/cmnd/POWER",
		"unit": "",
		"Subscribe": "loog/shufang/POWER",
		"cmdon": "on"
	}, {
		"title": "厨房",
		"id": "7",
		"group": "one",
		"key1": "POWER",
		"mode": "light",
		"stat": "OFF",
		"JSON": "loog/chufang/STATE",
		"name": "chufang",
		"cmdoff": "off",
		"Publish": "loog/chufang/cmnd/POWER",
		"unit": "",
		"Subscribe": "loog/chufang/POWER",
		"cmdon": "on"
	}, {
		"title": "门口灯",
		"id": "8",
		"group": "one",
		"key1": "POWER",
		"mode": "light",
		"stat": "OFF",
		"JSON": "loog/menkou/STATE",
		"name": "menkou",
		"cmdoff": "off",
		"Publish": "loog/menkou/cmnd/POWER",
		"unit": "",
		"Subscribe": "loog/menkou/POWER",
		"cmdon": "on"
	}, {
		"title": "温度",
		"id": "10",
		"group": "two",
		"key1": "DHT11",
		"mode": "sensor",
		"stat": 35.0,
		"JSON": "loog/wskg/SENSOR",
		"name": "Temperature",
		"cmdoff": "off",
		"group_title": "二楼",
		"Publish": "Temperature",
		"unit": "°C",
		"Subscribe": "loog/wskg/SENSOR",
		"cmdon": 30.8
	}, {
		"title": "湿度",
		"id": "11",
		"group": "two",
		"key1": "DHT11",
		"mode": "sensor",
		"stat": 88.0,
		"JSON": "loog/wskg/SENSOR",
		"name": "Humidity",
		"cmdoff": "off",
		"Publish": "Humidity",
		"unit": "%",
		"Subscribe": "loog/wskg/SENSOR",
		"cmdon": 95.0
	}, {
		"title": "结露点",
		"id": "121",
		"group": "two",
		"key1": "DHT11",
		"mode": "sensor",
		"stat": 32.7,
		"JSON": "loog/wskg/SENSOR",
		"name": "DewPoint",
		"cmdoff": "off",
		"Publish": "DewPoint",
		"unit": "°C",
		"Subscribe": "loog/wskg/SENSOR",
		"cmdon": 29.9
	}, {
		"title": "卧室电源开关",
		"id": "12",
		"group": "two",
		"key1": "POWER",
		"mode": "switch",
		"stat": "OFF",
		"JSON": "loog/wskg/STATE",
		"name": "wskg",
		"cmdoff": "off",
		"Publish": "loog/wskg/cmnd/POWER",
		"unit": "",
		"Subscribe": "loog/wskg/POWER",
		"cmdon": "on"
	}, {
		"title": "门锁",
		"id": "1585534260987",
		"group": "one",
		"key1": "POWER",
		"mode": "lock",
		"stat": "OFF",
		"JSON": "",
		"name": "door",
		"cmdoff": "OFF",
		"Publish": "loog/door/C",
		"unit": "%",
		"Subscribe": "loog/door/I",
		"cmdon": "ON"
	}],
	"mode": [{
		"title": "灯",
		"mode": "light",
		"ioc": "fa-lightbulb-o",
		"type": "switch"
	}, {
		"title": "遥控器",
		"mode": "ir",
		"ioc": "fa-feed",
		"type": "ir"
	}, {
		"title": "门锁",
		"mode": "lock",
		"ioc": "fa-lock",
		"type": "switch"
	}, {
		"title": "传感器",
		"mode": "sensor",
		"ioc": "fa-thermometer-1",
		"type": "number"
	}, {
		"title": "开关",
		"mode": "switch",
		"ioc": "fa-toggle-on",
		"type": "switch"
	}],
	"time": [],
	"mqtt": {
		"url": "192.168.2.1",
		"id": "web",
		"cleansession": true,
		"user": "user",
		"path": "/mqtt",
		"topic": "#",
		"mtport": "1883",
		"reconnectTimeout": "3000",
		"port": "10001",
		"pass": "110",
		"tls": false
	}
}
